bhargabhellopkg/__init__.py
bhargabhellopkg/bhargab2.py
bhargabhellopkg-0.0.7.dist-info/LICENSE
bhargabhellopkg-0.0.7.dist-info/METADATA
bhargabhellopkg-0.0.7.dist-info/WHEEL
bhargabhellopkg-0.0.7.dist-info/top_level.txt
bhargabhellopkg-0.0.7.dist-info/RECORD
